odoo10_addon_account_permanent_lock_move_update-10.0.1.0.1-nspkg.pth
odoo/addons/account_permanent_lock_move_update/README.rst
odoo/addons/account_permanent_lock_move_update/__init__.py
odoo/addons/account_permanent_lock_move_update/__manifest__.py
odoo/addons/account_permanent_lock_move_update/i18n/account_permanent_lock_move_update.pot
odoo/addons/account_permanent_lock_move_update/i18n/hr.po
odoo/addons/account_permanent_lock_move_update/i18n/hr_HR.po
odoo/addons/account_permanent_lock_move_update/static/description/icon.png
odoo/addons/account_permanent_lock_move_update/tests/__init__.py
odoo/addons/account_permanent_lock_move_update/tests/test_account_permanent_lock_move_update.py
odoo/addons/account_permanent_lock_move_update/wizards/__init__.py
odoo/addons/account_permanent_lock_move_update/wizards/account_update_lock_date.py
odoo/addons/account_permanent_lock_move_update/wizards/account_update_lock_date.xml
odoo/addons/account_permanent_lock_move_update/wizards/permanent_lock_date_wizard.py
odoo10_addon_account_permanent_lock_move_update-10.0.1.0.1.dist-info/METADATA
odoo10_addon_account_permanent_lock_move_update-10.0.1.0.1.dist-info/WHEEL
odoo10_addon_account_permanent_lock_move_update-10.0.1.0.1.dist-info/namespace_packages.txt
odoo10_addon_account_permanent_lock_move_update-10.0.1.0.1.dist-info/top_level.txt
odoo10_addon_account_permanent_lock_move_update-10.0.1.0.1.dist-info/RECORD
