Metadata-Version: 2.1
Name: odoo10-addon-account-permanent-lock-move-update
Version: 10.0.1.0.1
Summary: Allow an Account adviser to update permanent lock date without having access to all technical settings
Home-page: https://github.com/OCA/account-financial-tools
Author: ACSONE SA/NV, Odoo Community Association (OCA)
Author-email: support@odoo-community.org
License: AGPL-3
Platform: UNKNOWN
Classifier: Programming Language :: Python
Classifier: Framework :: Odoo
Classifier: License :: OSI Approved :: GNU Affero General Public License v3
Requires-Python: ~=2.7
Requires-Dist: odoo10-addon-account-lock-date-update
Requires-Dist: odoo10-addon-account-permanent-lock-move
Requires-Dist: odoo (<10.1dev,>=10.0)
